chatrooms/__init__.py
chatrooms/channels.py
chatrooms/client.py
chatrooms/exceptions.py
chatrooms/py.typed
chatrooms/taskiq.py
chatrooms/utils.py
vectman_chatrooms-1.0a11.dist-info/METADATA
vectman_chatrooms-1.0a11.dist-info/WHEEL
vectman_chatrooms-1.0a11.dist-info/entry_points.txt
vectman_chatrooms-1.0a11.dist-info/RECORD
