Metadata-Version: 2.1
Name: vectman-chatrooms
Version: 1.0a11
Summary: 
Author: Francisco Del Roio
Author-email: francipvb@hotmail.com
Requires-Python: >=3.11,<4.0
Classifier: Programming Language :: Python :: 3
Classifier: Programming Language :: Python :: 3.11
Provides-Extra: taskiq
Requires-Dist: chatrooms-api-client (>=1.1.1,<2.0.0)
Requires-Dist: plans (>=1.4.0,<2.0.0)
Requires-Dist: py-optional (>=1.0.1,<2.0.0)
Requires-Dist: pydantic[dotenv] (>=1.10.0,<2.0.0) ; extra == "taskiq"
Requires-Dist: taskiq (>=0.8.6,<0.9.0) ; extra == "taskiq"
Requires-Dist: users (>=1.4.4,<2.0.0)
